k2u_ops_xx/__init__.py
k2u_ops_xx/op_xx_yy/__init__.py
k2u_ops_xx/op_xx_yy/op_xx_yy.json
k2u_ops_xx/op_xx_yy/op_xx_yy.py
k2u_ops_xx/test/__init__.py
k2u_ops_xx/test/test_xx.py
k2u_ops_xx-0.0.1.dist-info/LICENSE.txt
k2u_ops_xx-0.0.1.dist-info/METADATA
k2u_ops_xx-0.0.1.dist-info/WHEEL
k2u_ops_xx-0.0.1.dist-info/dependency_links.txt
k2u_ops_xx-0.0.1.dist-info/top_level.txt
k2u_ops_xx-0.0.1.dist-info/RECORD
